setup.py
tornados_wake/__init__.py
tornados_wake.egg-info/PKG-INFO
tornados_wake.egg-info/SOURCES.txt
tornados_wake.egg-info/dependency_links.txt
tornados_wake.egg-info/requires.txt
tornados_wake.egg-info/top_level.txt