Metadata-Version: 1.1
Name: tornados-wake
Version: 0.1.0
Summary: Tornado's Wake: Handler and tools for inspecting routes of a tornado server
Home-page: https://github.com/jonmcoe/tornados-wake
Author: Jon Coe
Author-email: jonmcoe@gmail.com
License: UNKNOWN
Keywords: tornado tornadoweb routes handlers index
Platform: UNKNOWN
Classifier: Programming Language :: Python
Classifier: Programming Language :: Python :: 3
